binance_sdk_nft/__init__.py
binance_sdk_nft/metadata.py
binance_sdk_nft/nft.py
binance_sdk_nft/rest_api/__init__.py
binance_sdk_nft/rest_api/api/__init__.py
binance_sdk_nft/rest_api/api/nft_api.py
binance_sdk_nft/rest_api/models/__init__.py
binance_sdk_nft/rest_api/models/enums.py
binance_sdk_nft/rest_api/models/get_nft_asset_response.py
binance_sdk_nft/rest_api/models/get_nft_asset_response_list_inner.py
binance_sdk_nft/rest_api/models/get_nft_deposit_history_response.py
binance_sdk_nft/rest_api/models/get_nft_deposit_history_response_list_inner.py
binance_sdk_nft/rest_api/models/get_nft_transaction_history_response.py
binance_sdk_nft/rest_api/models/get_nft_transaction_history_response_list_inner.py
binance_sdk_nft/rest_api/models/get_nft_transaction_history_response_list_inner_tokens_inner.py
binance_sdk_nft/rest_api/models/get_nft_withdraw_history_response.py
binance_sdk_nft/rest_api/models/get_nft_withdraw_history_response_list_inner.py
binance_sdk_nft/rest_api/rest_api.py
binance_sdk_nft-2.2.0.dist-info/METADATA
binance_sdk_nft-2.2.0.dist-info/WHEEL
binance_sdk_nft-2.2.0.dist-info/licenses/LICENCE
binance_sdk_nft-2.2.0.dist-info/RECORD
